[
    "div",
    {
        "className": "content-wrapper"
    },
    [
        "header",
        {
            "className": "lesson-header"
        },
        [
            "p",
            {
                "className": "lesson-meta"
            },
            "Lesson 6"
        ],
        [
            "h1",
            {},
            "Regular Verbs I (-ar)"
        ]
    ],
    [
        "article",
        {},
        [
            "p",
            {
                "className": "section-intro"
            },
            "In Spanish, verbs are categorized by their endings: -ar, -er, or -ir. This lesson focuses on the most common group: -ar verbs."
        ],
        [
            "section",
            {
                "className": "module-section"
            },
            [
                "h2",
                {},
                "Conjugation Pattern"
            ],
            [
                "p",
                {},
                "To conjugate a regular -ar verb in the present tense, remove the -ar to find the stem, then add the following endings:"
            ],
            [
                "table",
                {},
                [
                    "thead",
                    {},
                    [
                        "tr",
                        {},
                        [
                            "th",
                            {},
                            "Subject"
                        ],
                        [
                            "th",
                            {},
                            "Ending"
                        ],
                        [
                            "th",
                            {},
                            "Example (Hablar)"
                        ]
                    ]
                ],
                [
                    "tbody",
                    {},
                    [
                        "tr",
                        {},
                        [
                            "td",
                            {},
                            "Yo"
                        ],
                        [
                            "td",
                            {},
                            [
                                "strong",
                                {},
                                "-o"
                            ]
                        ],
                        [
                            "td",
                            {
                                "className": "spanish"
                            },
                            "hablo"
                        ]
                    ],
                    [
                        "tr",
                        {},
                        [
                            "td",
                            {},
                            "Tú"
                        ],
                        [
                            "td",
                            {},
                            [
                                "strong",
                                {},
                                "-as"
                            ]
                        ],
                        [
                            "td",
                            {
                                "className": "spanish"
                            },
                            "hablas"
                        ]
                    ],
                    [
                        "tr",
                        {},
                        [
                            "td",
                            {},
                            "Él / Ella / Ud."
                        ],
                        [
                            "td",
                            {},
                            [
                                "strong",
                                {},
                                "-a"
                            ]
                        ],
                        [
                            "td",
                            {
                                "className": "spanish"
                            },
                            "habla"
                        ]
                    ],
                    [
                        "tr",
                        {},
                        [
                            "td",
                            {},
                            "Nosotros/as"
                        ],
                        [
                            "td",
                            {},
                            [
                                "strong",
                                {},
                                "-amos"
                            ]
                        ],
                        [
                            "td",
                            {
                                "className": "spanish"
                            },
                            "hablamos"
                        ]
                    ],
                    [
                        "tr",
                        {},
                        [
                            "td",
                            {},
                            "Vosotros/as"
                        ],
                        [
                            "td",
                            {},
                            [
                                "strong",
                                {},
                                "-áis"
                            ]
                        ],
                        [
                            "td",
                            {
                                "className": "spanish"
                            },
                            "habláis"
                        ]
                    ],
                    [
                        "tr",
                        {},
                        [
                            "td",
                            {},
                            "Ellos / Ellas / Uds."
                        ],
                        [
                            "td",
                            {},
                            [
                                "strong",
                                {},
                                "-an"
                            ]
                        ],
                        [
                            "td",
                            {
                                "className": "spanish"
                            },
                            "hablan"
                        ]
                    ]
                ]
            ]
        ]
    ]
]