[
  "div",
  {
    "className": "content-wrapper"
  },
  [
    "h1",
    {},
    "Definite Article II"
  ],
  [
    "p",
    {},
    "In Spanish, the definite article (el, la, los, las) is used in several situations where it is omitted in English."
  ],
  [
    "h2",
    {},
    "Special Uses"
  ],
  [
    "ul",
    {
      "className": "phrase-list"
    },
    [
      "li",
      {},
      [
        "span",
        {
          "className": "spanish"
        },
        [
          [
            "strong",
            {},
            "With abstract nouns"
          ],
          ": El amor es importante."
        ]
      ],
      [
        "span",
        {
          "className": "meaning"
        },
        "Love is important."
      ]
    ],
    [
      "li",
      {},
      [
        "span",
        {
          "className": "spanish"
        },
        [
          [
            "strong",
            {},
            "With days of the week"
          ],
          ": El lunes voy al cine."
        ]
      ],
      [
        "span",
        {
          "className": "meaning"
        },
        "On Monday I'm going to the cinema."
      ]
    ],
    [
      "li",
      {},
      [
        "span",
        {
          "className": "spanish"
        },
        [
          [
            "strong",
            {},
            ""
          ],
          "With titles"
        ]
      ],
      [
        "span",
        {
          "className": "meaning"
        },
        [
          "when talking about someone)",
          [
            "strong",
            {},
            ""
          ],
          ": El doctor García está aquí. (Dr. Garcia is here."
        ]
      ]
    ],
    [
      "li",
      {},
      [
        "span",
        {
          "className": "spanish"
        },
        [
          [
            "strong",
            {},
            "With body parts and clothing"
          ]
        ]
      ],
      [
        "span",
        {
          "className": "meaning"
        },
        "replaces possessive adjectives): Me lavo las manos. (I wash my hands."
      ]
    ]
  ]
]